trend_classifier/__init__.py
trend_classifier-0.1.11.dist-info/LICENSE
trend_classifier-0.1.11.dist-info/METADATA
trend_classifier-0.1.11.dist-info/WHEEL
trend_classifier-0.1.11.dist-info/top_level.txt
trend_classifier-0.1.11.dist-info/RECORD
