Metadata-Version: 2.1
Name: trend-classifier
Version: 0.1.11
Summary: Package for automated signal segmentation, trend classification and analysis.
Author-email: Krystian Safjan <ksafjan@gmail.com>
License: MIT
Project-URL: Source, https://github.com/izikeros/trend_classifier
Project-URL: Bug Tracker, https://github.com/izikeros/trend_classifier/issues
Keywords: trend,timeseries,classification,segmentation,analysis,algotrading,finance
Classifier: Development Status :: 3 - Alpha
Classifier: Intended Audience :: Developers
Classifier: Intended Audience :: Science/Research
Classifier: Intended Audience :: Financial and Insurance Industry
Classifier: License :: OSI Approved :: MIT License
Classifier: Programming Language :: Python :: 3
Classifier: Programming Language :: Python :: 3.7
Classifier: Programming Language :: Python :: 3.8
Classifier: Programming Language :: Python :: 3.9
Classifier: Programming Language :: Python :: 3.10
Classifier: Programming Language :: Python :: 3.11
Classifier: Programming Language :: Python :: 3.12
Classifier: Programming Language :: Python :: 3 :: Only
Classifier: Topic :: Software Development :: Libraries :: Python Modules
Classifier: Topic :: Utilities
Requires-Python: <=3.13,>=3.7
License-File: LICENSE
Requires-Dist: matplotlib >=3.8.3
Requires-Dist: pydantic >=2.6.4
Requires-Dist: numpy >=1.26.4
Requires-Dist: pandas >=2.2.1
